kilvin/__init__.py
kilvin/__main__.py
kilvin/configs.py
kilvin/log.py
kilvin/utils.py
kilvin/cmds/__init__.py
kilvin/cmds/build.py
kilvin/cmds/init.py
kilvin/cmds/new.py
kilvin/cmds/server.py
kilvin/render/__init__.py
kilvin/render/builder.py
kilvin/render/feed.py
kilvin/render/page.py
kilvin-0.4.dist-info/LICENSE
kilvin-0.4.dist-info/METADATA
kilvin-0.4.dist-info/WHEEL
kilvin-0.4.dist-info/entry_points.txt
kilvin-0.4.dist-info/top_level.txt
kilvin-0.4.dist-info/RECORD
