Metadata-Version: 2.1
Name: kilvin
Version: 0.4
Summary: A minimal static site generator.
Author-email: Pratham Singh <prathms007@gmail.com>
Project-URL: Homepage, https://github.com/shanukun/kilvin
Project-URL: Bug Tracker, https://github.com/shanukun/kilvin/issues
Keywords: static site generator,markdow
Classifier: Programming Language :: Python :: 3
Classifier: License :: OSI Approved :: MIT License
Requires-Python: >=3.9
License-File: LICENSE
Requires-Dist: markdown (==3.4.3)
Requires-Dist: Jinja2
Requires-Dist: tomli
Requires-Dist: python-frontmatter
Requires-Dist: click
Provides-Extra: dev
Requires-Dist: black ; extra == 'dev'
Requires-Dist: bumpver ; extra == 'dev'
Requires-Dist: isort ; extra == 'dev'
Requires-Dist: pip-tools ; extra == 'dev'
Requires-Dist: pytest ; extra == 'dev'
